{"key":"Burundi","es":"Burundi","iso":"bi","iso2":"BI","center":[-3.4,29.9],"zoom":8,"capital":"Gitega","capital_real":"Gitega","tiles":3,"tileNames":["Gitega","Kayanza","Muyinga"],"region":"Africa","subregion":"Eastern Africa","continent":"África","poblacion":14048000,"poblacion_fmt":"14M","pib_m":4838,"pib_m_fmt":"4,838","pib_pc":344,"pib_pc_fmt":"344","deuda_pct":"53.06%","idh":"0.420","area_km2":27834,"anio":"2025*","fuentes":["dossier_datosmacro","worldbank_pop_2024","worldbank_gdp_2023","apicountries"],"military":{"defense_pct_pib":1.2,"defense_m_usd":59,"troops_est":51697,"power_index":4.15,"note":"Estimación educativa derivada de PIB/población/IDH — no es dato oficial"},"socio":{"life_expectancy":65,"literacy_pct":65,"gini_est":47,"co2_t_pc_est":0.6,"note":"Indicadores proxy educativos (no oficiales)"},"cities":[{"n":1,"name":"Gitega","capital":true,"lat":-3.42708,"lon":29.92463,"geoLabel":"Gitega"},{"n":2,"name":"Kayanza","lat":-2.9221,"lon":29.6293,"geoLabel":"Kayanza"},{"n":3,"name":"Muyinga","lat":-2.8451,"lon":30.3414,"geoLabel":"Muyinga"}],"regions":[{"name":"Bubanza","color":"#e57373","type":"Province","geonunit":"Burundi"},{"name":"Buyumbura Mairie","color":"#f06292","type":"Province","geonunit":"Burundi"},{"name":"Buyumbura Rural","color":"#ba68c8","type":"Province","geonunit":"Burundi"},{"name":"Bururi","color":"#9575cd","type":"Province","geonunit":"Burundi"},{"name":"Cankuzo","color":"#7986cb","type":"Province","geonunit":"Burundi"},{"name":"Cibitoke","color":"#64b5f6","type":"Province","geonunit":"Burundi"},{"name":"Gitega","color":"#4fc3f7","type":"Province","geonunit":"Burundi"},{"name":"Karuzi","color":"#4dd0e1","type":"Province","geonunit":"Burundi"},{"name":"Kayanza","color":"#4db6ac","type":"Province","geonunit":"Burundi"},{"name":"Kirundo","color":"#81c784","type":"Province","geonunit":"Burundi"},{"name":"Makamba","color":"#aed581","type":"Province","geonunit":"Burundi"},{"name":"Muramvya","color":"#dce775","type":"Province","geonunit":"Burundi"},{"name":"Muyinga","color":"#fff176","type":"Province","geonunit":"Burundi"},{"name":"Mwaro","color":"#ffd54f","type":"Province","geonunit":"Burundi"},{"name":"Ngozi","color":"#ffb74d","type":"Province","geonunit":"Burundi"},{"name":"Rutana","color":"#ff8a65","type":"Province","geonunit":"Burundi"},{"name":"Ruyigi","color":"#a1887f","type":"Province","geonunit":"Burundi"}],"hasBorder":true,"hasAdmin":true,"borderUrl":"assets/borders/bi.json","regionsUrl":"assets/admin1/bi.json","flagUrl":"https://flagcdn.com/w160/bi.png","flagUrl40":"https://flagcdn.com/w40/bi.png"}